vulners/__init__.py
vulners/base.py
vulners/vscanner.py
vulners/vulners/__init__.py
vulners/vulners/archive.py
vulners/vulners/audit.py
vulners/vulners/misc.py
vulners/vulners/report.py
vulners/vulners/search.py
vulners/vulners/subscription.py
vulners/vulners/subscription_v4.py
vulners/vulners/webhook.py
vulners-3.1.2.dist-info/METADATA
vulners-3.1.2.dist-info/WHEEL
vulners-3.1.2.dist-info/licenses/AUTHORS
vulners-3.1.2.dist-info/licenses/LICENSE
vulners-3.1.2.dist-info/RECORD
