Metadata-Version: 2.4
Name: vulners
Version: 3.1.2
Summary: Python library and command-line utility for Vulners (https://vulners.com)
License-File: AUTHORS
License-File: LICENSE
Keywords: security,network,vulners,vulnerability,CVE
Author: Vulners Team
Requires-Python: >=3.10
Classifier: Development Status :: 5 - Production/Stable
Classifier: Intended Audience :: Developers
Classifier: Intended Audience :: Information Technology
Classifier: License :: OSI Approved :: GNU General Public License v3 (GPLv3)
Classifier: Operating System :: OS Independent
Classifier: Programming Language :: Python
Classifier: Programming Language :: Python :: 3
Classifier: Programming Language :: Python :: 3.10
Classifier: Programming Language :: Python :: 3.11
Classifier: Programming Language :: Python :: 3.12
Classifier: Programming Language :: Python :: 3.13
Classifier: Programming Language :: Python :: 3.14
Classifier: Topic :: Software Development :: Libraries :: Python Modules
Classifier: Topic :: Software Development :: Version Control
Classifier: Topic :: Utilities
Requires-Dist: httpx (>=0.28.1,<0.29.0)
Requires-Dist: orjson (>=3.10.18,<4.0.0)
Requires-Dist: pydantic (>=2.11.4,<3.0.0)
